odoo/addons/hr_branch/README.rst
odoo/addons/hr_branch/__init__.py
odoo/addons/hr_branch/__manifest__.py
odoo/addons/hr_branch/i18n/de.po
odoo/addons/hr_branch/i18n/es.po
odoo/addons/hr_branch/i18n/hr_branch.pot
odoo/addons/hr_branch/i18n/it.po
odoo/addons/hr_branch/models/__init__.py
odoo/addons/hr_branch/models/hr_department.py
odoo/addons/hr_branch/readme/CONTRIBUTORS.rst
odoo/addons/hr_branch/readme/DESCRIPTION.rst
odoo/addons/hr_branch/static/description/icon.png
odoo/addons/hr_branch/static/description/index.html
odoo/addons/hr_branch/views/hr_department_views.xml
odoo/addons/hr_branch/views/hr_employee_views.xml
odoo_addon_hr_branch-15.0.1.0.0.7.dist-info/METADATA
odoo_addon_hr_branch-15.0.1.0.0.7.dist-info/WHEEL
odoo_addon_hr_branch-15.0.1.0.0.7.dist-info/top_level.txt
odoo_addon_hr_branch-15.0.1.0.0.7.dist-info/RECORD
