Metadata-Version: 2.1
Name: odoo-addon-hr-branch
Version: 15.0.1.0.0.7
Summary: Allow define company branch for employee process
Home-page: https://github.com/OCA/hr
Author: Vauxoo, Odoo Community Association (OCA)
Author-email: support@odoo-community.org
License: LGPL-3
Platform: UNKNOWN
Classifier: Programming Language :: Python
Classifier: Framework :: Odoo
Classifier: Framework :: Odoo :: 15.0
Classifier: License :: OSI Approved :: GNU Lesser General Public License v3 (LGPLv3)
Classifier: Development Status :: 6 - Mature
Requires-Python: >=3.8
Requires-Dist: odoo <15.1dev,>=15.0a
